flops_utils/env_vars.py
flops_utils/logging.py
flops_utils/ml_model_flavor_proxy.py
flops_utils/ml_repo_building_blocks/__init__.py
flops_utils/ml_repo_building_blocks/flops_learner_files_proxy.py
flops_utils/ml_repo_files_proxy.py
flops_utils/ml_repo_templates.py
flops_utils/mqtt_topics.py
flops_utils/notifications.py
flops_utils/shell.py
flops_utils/timer.py
flops_utils/types.py
flops_utils-0.6.3.dist-info/METADATA
flops_utils-0.6.3.dist-info/WHEEL
flops_utils-0.6.3.dist-info/RECORD
