Metadata-Version: 2.3
Name: flops_utils
Version: 0.6.3
Summary: A library containing common utilities for FLOps
Author: Alexander Malyuk
Author-email: malyuk.alexander1999@gmail.com
Requires-Python: >=3.10,<4.0
Classifier: Programming Language :: Python :: 3
Classifier: Programming Language :: Python :: 3.10
Classifier: Programming Language :: Python :: 3.11
Classifier: Programming Language :: Python :: 3.12
Classifier: Programming Language :: Python :: 3.13
Requires-Dist: paho-mqtt (==2.0)
